fcmaes/__init__.py
fcmaes/advretry.py
fcmaes/astro.py
fcmaes/bitecpp.py
fcmaes/cmaes.py
fcmaes/cmaescpp.py
fcmaes/crfmnes.py
fcmaes/crfmnescpp.py
fcmaes/dacpp.py
fcmaes/de.py
fcmaes/decpp.py
fcmaes/diversifier.py
fcmaes/evaluator.py
fcmaes/journal.py
fcmaes/mapelites.py
fcmaes/mode.py
fcmaes/modecpp.py
fcmaes/moretry.py
fcmaes/multiretry.py
fcmaes/optimizer.py
fcmaes/pgpecpp.py
fcmaes/pygmoretry.py
fcmaes/retry.py
fcmaes/test_cma.py
fcmaes/testfun.py
fcmaes/lib/libacmalib.dll
fcmaes/lib/libacmalib.dylib
fcmaes/lib/libacmalib.so
fcmaes/lib/libhbv.so
fcmaes/lib/liblrgv.so
fcmaes/lib/librw_top_trumps.dll
fcmaes/lib/librw_top_trumps.so
fcmaes-1.6.11.dist-info/LICENSE
fcmaes-1.6.11.dist-info/METADATA
fcmaes-1.6.11.dist-info/WHEEL
fcmaes-1.6.11.dist-info/top_level.txt
fcmaes-1.6.11.dist-info/RECORD
