Metadata-Version: 2.1
Name: fcmaes
Version: 1.6.11
Summary: A Python 3 gradient-free optimization library.
Home-page: https://github.com/dietmarwo/fast-cma-es
Author: Dietmar Wolz
Author-email: drdietmarwolz@yahoo.de
License: MIT
Keywords: optimization,multi-objective,parallel
Classifier: Intended Audience :: Manufacturing
Classifier: Intended Audience :: Financial and Insurance Industry
Classifier: Intended Audience :: Healthcare Industry
Classifier: Intended Audience :: Telecommunications Industry
Classifier: Intended Audience :: Information Technology
Classifier: Intended Audience :: Science/Research
Classifier: Intended Audience :: Education
Classifier: Topic :: Office/Business :: Financial
Classifier: Topic :: Office/Business :: Scheduling
Classifier: Topic :: Scientific/Engineering
Classifier: Topic :: Scientific/Engineering :: Information Analysis
Classifier: Topic :: Scientific/Engineering :: Mathematics
Classifier: Topic :: Scientific/Engineering :: Artificial Intelligence
Classifier: Operating System :: OS Independent
Classifier: Programming Language :: Python :: 3
Classifier: Development Status :: 5 - Production/Stable
Classifier: Environment :: Console
Classifier: License :: OSI Approved :: MIT License
Requires-Python: >=3.7
License-File: LICENSE
Requires-Dist: numpy
Requires-Dist: scipy
Requires-Dist: scikit-learn
Requires-Dist: threadpoolctl
Requires-Dist: numba
Requires-Dist: loguru
